cachian/__init__.py
cachian/memory_store.py
cachian/redis_store.py
cachian-0.3.dist-info/LICENSE
cachian-0.3.dist-info/METADATA
cachian-0.3.dist-info/WHEEL
cachian-0.3.dist-info/top_level.txt
cachian-0.3.dist-info/RECORD
